<dictionary>
    <item>
        <word>access</word>
        <definitions>
            <nouns>
                <defn>the ability, right, or permission to approach, enter, speak with, or use; admittance</defn>
                <defn>the state or quality of being approachable</defn>
                <defn>a way or means of approach</defn>
            </nouns>
        </definitions>
    </item>

    <item>
        <word>region</word>
        <definitions>
            <nouns>
                <defn>an extensive, continuous part of a surface, space, or body</defn>
                <defn>a part of the earth's surface (land or sea) of considerable and usually indefinite extent</defn>
                <defn>a district without respect to boundaries or extent</defn>
            </nouns>
        </definitions>
    </item>

    <item>
        <word>anybody</word>
        <definitions>
            <pronouns>
                <defn>any person</defn>
            </pronouns>
        </definitions>
    </item>

    <item>
        <word>between</word>
        <definitions>
            <prepositions>
                <defn>in the space separating (two points, objects, etc.): </defn>
            </prepositions>
            <adverbs>
                <defn>in the intervening space or time; in an intermediate position or relation</defn>
            </adverbs>
        </definitions>
    </item>

    <item>
        <word>book</word>
        <definitions>
            <nouns>
                <defn>a handwritten or printed work of fiction or nonfiction, usually on sheets of paper fastened or bound together within covers.</defn>
            </nouns>
        </definitions>
    </item>

    <item>
        <word>basketball</word>
        <definitions>
            <nouns>
                <defn>a game played by two teams of usually five players each on a rectangular court having a raised basket or goal at each end, points being scored by tossing the ball through the opponent's basket.</defn>
                <defn>the round, inflated ball approximately 30 inches (76 centimeters) in circumference, used in this game.</defn>
            </nouns>
        </definitions>
    </item>

    <item>
        <word>chance</word>
        <definitions>
            <nouns>
                <defn>the absence of any cause of events that can be predicted, understood, or controlled: often personified or treated as a positive agency</defn>
                <defn>luck or fortune</defn>
                <defn>a possibility or probability of anything happening</defn>
            </nouns>
        </definitions>
    </item>

    <item>
        <word>chocolate</word>
        <definitions>
            <nouns>
                <defn>a preparation of the seeds of cacao, roasted, husked, and ground, often sweetened and flavored, as with vanilla</defn>
                <defn>a beverage made by dissolving such a preparation in milk or water, served hot or cold</defn>
                <defn>candy made from such a preparation</defn>
            </nouns>
        </definitions>
    </item>

    <item>
        <word>day</word>
        <definitions>
            <nouns>
                <defn>the interval of light between two successive nights; the time between sunrise and sunset</defn>
            </nouns>
        </definitions>
    </item>

    <item>
        <word>decade</word>
        <definitions>
            <nouns>
                <defn>a period of ten years</defn>
            </nouns>
        </definitions>
    </item>

    <item>
        <word>decrease</word>
        <definitions>
            <verbs>
                <defn>to diminish or lessen in extent, quantity, strength, power, etc.</defn>
                <defn>to make less; cause to diminish</defn>
            </verbs>
        </definitions>
    </item>

    <item>
        <word>degree</word>
        <definitions>
            <nouns>
                <defn>any of a series of steps or stages, as in a process or course of action; a point in any scale.</defn>
                <defn>an academic title conferred by universities and colleges as an indication of the completion of a course of study, or as an honorary recognition of achievement.</defn>
            </nouns>
        </definitions>
    </item>
</dictionary>